delu/__init__.py
delu/_stream.py
delu/_tensor_ops.py
delu/_tools.py
delu/_utilities.py
delu/_utils.py
delu/cuda.py
delu/data.py
delu/exceptions.py
delu/hardware.py
delu/nn.py
delu/random.py
delu/tools.py
delu/tests/__init__.py
delu/tests/test__tensor_ops.py
delu/tests/test__utilities.py
delu/tests/test_cuda.py
delu/tests/test_data.py
delu/tests/test_nn.py
delu/tests/test_random.py
delu/tests/test_stream.py
delu/tests/test_tools.py
delu/tests/util.py
delu/utils/__init__.py
delu/utils/data.py
delu-0.0.26.dist-info/LICENSE
delu-0.0.26.dist-info/WHEEL
delu-0.0.26.dist-info/METADATA
delu-0.0.26.dist-info/RECORD
