Metadata-Version: 2.3
Name: delu
Version: 0.0.26
Summary: Deep Learning Utilities for PyTorch users.
Keywords: artificial intelligence,deep learning,library,python,pytorch,torch
Author: Yury Gorishniy
Requires-Python: >=3.9
Classifier: Intended Audience :: Developers
Classifier: Intended Audience :: Science/Research
Classifier: License :: OSI Approved :: MIT License
Classifier: Operating System :: MacOS
Classifier: Operating System :: Unix
Classifier: Programming Language :: Python :: 3
Classifier: Topic :: Scientific/Engineering :: Artificial Intelligence
Classifier: Topic :: Software Development :: Libraries :: Python Modules
Requires-Dist: numpy >=1.21,<3
Requires-Dist: torch >=1.9,<3
Project-URL: Code, https://github.com/Yura52/delu
Project-URL: Documentation, https://yura52.github.io/delu
